README.txt
bootstrap.py
buildout.cfg
setup.py
docs/HISTORY.txt
src/collective/__init__.py
src/collective.securitycleanup.egg-info/PKG-INFO
src/collective.securitycleanup.egg-info/SOURCES.txt
src/collective.securitycleanup.egg-info/dependency_links.txt
src/collective.securitycleanup.egg-info/entry_points.txt
src/collective.securitycleanup.egg-info/namespace_packages.txt
src/collective.securitycleanup.egg-info/not-zip-safe
src/collective.securitycleanup.egg-info/requires.txt
src/collective.securitycleanup.egg-info/top_level.txt
src/collective/securitycleanup/README.txt
src/collective/securitycleanup/__init__.py
src/collective/securitycleanup/configure.zcml
src/collective/securitycleanup/handler.py
src/collective/securitycleanup/testing.py
src/collective/securitycleanup/tests.py
src/collective/securitycleanup/profiles/default/collective.securitycleanup.txt