Metadata-Version: 1.0
Name: collective.securitycleanup
Version: 0.1
Summary: GenerecSetup handlers to restore Zope security to defaults
Home-page: http://pypi.python.org/pypi/collective.securitycleanup
Author: Ross Patterson
Author-email: me@rpatterson.net
License: GPL
Platform: UNKNOWN
Classifier: Programming Language :: Python
Classifier: Topic :: Software Development :: Libraries :: Python Modules
